{
    "TARGET_SYMBOL": "LTCUSDT",
    "TARGET_PREFIX": "LTCUSDT",
    "VERSION": "3.5",
    "SCHEDULE": {
        "asian": {
            "start": "00:00",
            "end": "07:00",
            "run_id": "run_20260424_014500_v3_asian_12",
            "config_id": "CFG_LTC_ASIAN_V3_5",
            "trading_config": {
                "min_prob_thresh": 0.55,
                "mse_thresh_perc": 80.0
            }
        }
    },
    "HF_CLOUD": {
        "DATASET_REPO": "dung5k/ltc_v3_tensor_asian",
        "MODEL_REPO": "dung5k/argo_data",
        "SYNC_CHUNKS": true
    },
    "FEATURE_ENGINEERING": {
        "TP_PCT": 0.003,
        "SL_PCT": 0.003,
        "MAX_HOLD_BARS": 12,
        "LABEL_MODE": "pct",
        "PIP_SIZE": 0.01,
        "WINDOW_SIZE": 20,
        "STEP_SIZE": 1,
        "CRYPTO_MODE": true,
        "MACRO_FEATURES": {
            "BTCUSDT": ["log_ret", "bb_width", "volume", "corr_60"],
            "ETHUSDT": ["log_ret", "volume", "corr_60"],
            "XRPUSDT": ["log_ret", "volume"],
            "BCHUSDT": ["log_ret"],
            "DOGEUSDT": ["log_ret", "volume"]
        },
        "ORDER_FLOW": false,
        "VOL_REGIME": true
    },
    "TRAINING": {
        "D_MODEL": 64,
        "N_HEAD": 4,
        "NUM_LAYERS": 2,
        "BATCH_SIZE": 256,
        "LEARNING_RATE": 3e-05,
        "DROPOUT": 0.4
    },
    "DATA_SOURCE": {
        "RAW_LOCAL_DIR": "data/history",
        "TIMEFRAME": "1m",
        "BROKERS": {
            "BINANCE": "BINANCE",
            "EXNESS": "D:\\mt5\\MetaTrader 5 EXNESS\\terminal64.exe"
        },
        "ROUTING": {
            "LTCUSDT": "BINANCE",
            "BTCUSDT": "BINANCE",
            "ETHUSDT": "BINANCE",
            "XRPUSDT": "BINANCE",
            "BCHUSDT": "BINANCE",
            "DOGEUSDT": "BINANCE"
        }
    },
    "LIVE_BOT": {
        "TRADE_PLATFORM": "BINANCE",
        "PAPER_TRADE": true,
        "MAX_ABSOLUTE_MSE": 0.8,
        "MIN_PROBABILITY_THRESH": 0.55,
        "VIRTUAL_EXECUTION": {
            "INITIAL_BALANCE": 1000,
            "LOT_SIZE": 0.5
        }
    }
}
